ln_studio/__init__.py
ln_studio/loading.py
ln_studio/main.py
ln_studio/migrate.py
ln_studio/components/__init__.py
ln_studio/components/collabsible.py
ln_studio/components/edit.py
ln_studio/components/edit_graph.py
ln_studio/components/edit_node.py
ln_studio/components/node_views.py
ln_studio/components/notification.py
ln_studio/components/page.py
ln_studio/components/page_parent.py
ln_studio/components/scroll_label.py
ln_studio/components/utils.py
ln_studio/components/views/__init__.py
ln_studio/components/views/matplotlib.py
ln_studio/components/views/pyqt.py
ln_studio/pages/__init__.py
ln_studio/pages/config.py
ln_studio/pages/debug.py
ln_studio/pages/home.py
ln_studio/pages/run.py
ln_studio/qtpydocking/__init__.py
ln_studio/qtpydocking/_version.py
ln_studio/qtpydocking/default.css
ln_studio/qtpydocking/default_linux.css
ln_studio/qtpydocking/dock_area_layout.py
ln_studio/qtpydocking/dock_area_tab_bar.py
ln_studio/qtpydocking/dock_area_title_bar.py
ln_studio/qtpydocking/dock_area_widget.py
ln_studio/qtpydocking/dock_container_widget.py
ln_studio/qtpydocking/dock_manager.py
ln_studio/qtpydocking/dock_overlay.py
ln_studio/qtpydocking/dock_splitter.py
ln_studio/qtpydocking/dock_widget.py
ln_studio/qtpydocking/dock_widget_tab.py
ln_studio/qtpydocking/eliding_label.py
ln_studio/qtpydocking/enums.py
ln_studio/qtpydocking/floating_dock_container.py
ln_studio/qtpydocking/floating_widget_title_bar.py
ln_studio/qtpydocking/util.py
ln_studio/qtpydocking/tests/__init__.py
ln_studio/qtpydocking/tests/conftest.py
ln_studio/qtpydocking/tests/test_examples.py
ln_studio/qtpynodeeditor/DefaultStyle.json
ln_studio/qtpynodeeditor/__init__.py
ln_studio/qtpynodeeditor/base.py
ln_studio/qtpynodeeditor/connection.py
ln_studio/qtpynodeeditor/connection_geometry.py
ln_studio/qtpynodeeditor/connection_graphics_object.py
ln_studio/qtpynodeeditor/connection_painter.py
ln_studio/qtpynodeeditor/data_model_registry.py
ln_studio/qtpynodeeditor/enums.py
ln_studio/qtpynodeeditor/exceptions.py
ln_studio-1.1.1.dist-info/licenses/LICENSE
ln_studio-1.1.1.dist-info/METADATA
ln_studio-1.1.1.dist-info/WHEEL
ln_studio-1.1.1.dist-info/entry_points.txt
ln_studio-1.1.1.dist-info/top_level.txt
ln_studio-1.1.1.dist-info/zip-safe
ln_studio-1.1.1.dist-info/RECORD
