Metadata-Version: 2.4
Name: LN-Studio
Version: 1.1.1
Summary: LN-Studio: QT based GUI for livenodes projects.
Author-email: Yale Hartmann <yale.hartmann@uni-bremen.de>
License-Expression: GPL-3.0-only
License-File: LICENSE
Requires-Dist: livenodes>=1.1.3
Requires-Dist: seaborn>=0.11.2
Requires-Dist: networkx>2.6.3
Requires-Dist: numpy>=1.22.1
Requires-Dist: matplotlib>=3.5.1
Requires-Dist: QtPy>=2.4.1
Requires-Dist: PyQt5>=5.12.3
Requires-Dist: python_qnotifications>=2.0.6
Requires-Dist: appdirs>=1.4.4
Requires-Dist: darkdetect
Requires-Dist: pyqtdarktheme-fork>=2.1.0
Requires-Dist: click
Provides-Extra: dev
Requires-Dist: tox; extra == "dev"
Requires-Dist: pytest>=7.0.1; extra == "dev"
Dynamic: license-file
